freshenv/__init__.py
freshenv/build.py
freshenv/check.py
freshenv/clean.py
freshenv/cli.py
freshenv/console.py
freshenv/flavours.py
freshenv/provision.py
freshenv/remove.py
freshenv/start.py
freshenv/util.py
freshenv/view.py
freshenv/cloud/__init__.py
freshenv/cloud/cloud.py
freshenv/cloud/config.py
freshenv/cloud/fetch.py
freshenv/cloud/ls.py
freshenv/cloud/push.py
freshenv-3.0.2.dist-info/LICENSE
freshenv-3.0.2.dist-info/METADATA
freshenv-3.0.2.dist-info/WHEEL
freshenv-3.0.2.dist-info/entry_points.txt
freshenv-3.0.2.dist-info/top_level.txt
freshenv-3.0.2.dist-info/RECORD
