Metadata-Version: 2.1
Name: freshenv
Version: 3.0.2
Summary: A cli to provision and manage local developer environments.
Home-page: https://github.com/raiyanyahya/freshenv
Author: Raiyan Yahya
Author-email: raiyanyahyadeveloper@gmail.com
License: Mozilla Public License 2.0
Keywords: cli,developer tools,productivity,tools
Platform: UNKNOWN
Requires-Python: >3.5
Requires-Dist: click (==8.1.3)
Requires-Dist: docker (==6.0.1)
Requires-Dist: rich (==12.5.1)
Requires-Dist: dockerpty (==0.4.1)
Requires-Dist: configparser (==5.3.0)
Requires-Dist: Jinja2 (==3.1.2)
Requires-Dist: boto3 (==1.26.1)
